<?xml version="1.0" encoding="utf-8"?>
<!DOCTYPE hibernate-mapping PUBLIC "-//Hibernate/Hibernate Mapping DTD 3.0//EN"
"http://hibernate.sourceforge.net/hibernate-mapping-3.0.dtd">
<!-- 
    Mapping file autogenerated by MyEclipse Persistence Tools
-->
<hibernate-mapping>
    <class name="com.ovt.idtv.boss.sms.db.OvtSmsInc" table="OVT_SMS_INC" >
        <id name="id" type="java.lang.Long">
            <column name="ID" precision="10" scale="0" />
            <generator class="assigned" />
        </id>
        <property name="incName" type="java.lang.String">
            <column name="INC_NAME" length="30" not-null="true" />
        </property>
        <property name="incPrice" type="java.lang.Double">
            <column name="INC_PRICE" precision="12" />
        </property>
        <property name="incType" type="java.lang.Integer">
            <column name="INC_TYPE" precision="1" scale="0" not-null="true" />
        </property>
        <property name="former" type="java.lang.String">
            <column name="FORMER" length="30" />
        </property>
        <property name="defaultFlag" type="java.lang.Integer">
            <column name="DEFAULT_FLAG" precision="1" scale="0" not-null="true" />
        </property>
        <property name="appendType" type="java.lang.Integer">
            <column name="APPEND_TYPE" precision="5" scale="0" />
        </property>
        <property name="appendContent" type="java.lang.String">
            <column name="APPEND_CONTENT" length="200" />
        </property>
        <property name="ordering" type="java.lang.Long">
            <column name="ORDERING" precision="10" scale="0" />
        </property>
    </class>
</hibernate-mapping>
